nenef/__init__.py
nenef-1.0.6.dist-info/LICENSE
nenef-1.0.6.dist-info/METADATA
nenef-1.0.6.dist-info/WHEEL
nenef-1.0.6.dist-info/top_level.txt
nenef-1.0.6.dist-info/RECORD
