Metadata-Version: 2.1
Name: nenef
Version: 1.0.6
Summary: This is module for neuronetworks
Home-page: https://github.com/ktotozdesest/nenef
Author: ktotozdesest
Author-email: kto00210@gmail.com
Project-URL: Documentation, https://github.com/ktotozdesest/nenef
Keywords: python neuronetworks neurenet
Classifier: Programming Language :: Python :: 3.12
Classifier: License :: OSI Approved :: MIT License
Classifier: Operating System :: OS Independent
Requires-Python: >=3.7
License-File: LICENSE
Requires-Dist: numpy >=1.24.1
